{
  "type": "Reconstructor",
  "name": "[blue]Human Medium Progression",
  "description": "Medium create.",
  "health": 800,
  "size": 4,
  "constructTime": 480,
  "upgrades": [
    ["human-machine-gun", "human-bullet-storm"],
    ["human-stun-gun", "human-flared-gun"],
    ["human-mono", "human-poly"]
    ],
  "consumes": {
      "items": {
          "items": [
            "gen-evolutionary/400"
          ]
      }
  },
  "requirements": [
    "gen-human/1600"
  ],
  "category": "units",
  "research": "human-low-progression"
}
