{
"type": "tank",
"name": "[blue]Human Tank",
"description": "Human Tank.",
"treadPullOffset": 5,
"speed": 0.7,
"rotateSpeed": 2.6,
"health": 400,
"armor": 20,
"itemCapacity": 0,
"hitSize": 18,
"researchCostMultiplier": 0,
"weapons": [
    {
        "name": "human-tank-weapon",
        "mirror": false,
        "shootY": 0,
        "x": 0,
        "y": 0,
        "reload": 36,
        "rotate": true,
        "shootSound": "sap",
        "bullet": {
          "type": "SapBulletType",
          "damage": 25,
          "length": 100,
          "sapStrength": "4",
          "shootEffect": "shootLiquid",
          "hitEffect": "hitLiquid",
          "color": "62AE7F",
          "lightColor": "84F491",
          "knockback": -5
        }
    }
]
}