{
  "type": "mech",
  "name": "[red]Zomber King",
  "description": "Zomber King.",
  "speed": 0.5,
  "rotate": true,
  "rotateSpeed" : 1,
  "research": "zomber-high-progression",
  "canAttack": false,
  "armor": 350,
  "health": 7000,
  "flying": false,
  "itemCapacity": 200,
  "hitSize": 20,
  "outlineColor": 543636,
  "weapons": [
    {
      "name": "zomber-king-hand",
      "x": 8,
      "y": 12,
      "reload": 18,
      "recoil": -4,
      "top": false,
      "alternate": true,
      "heatColor": "543636",
      "shootY": 8,
      "shootX": 12,
      "shootSound": "claws-wave",
      "bullet": {
      "type": "ShrapnelBulletType",
      "length": 16,
      "width": 0,
      "serrations": 0,
      "damage": 100,
      "hitColor": "633F3F",
      "status": "slow",
      "hitSound": "malignShoot",
      "shootEffect": "none",
      "smokeEffect": "none",
      "recoil": -1,
      "hitShake": 8,
      "maxRange": 64,
      "range": 64,
      "rangeOverride": 64
    }
  },
  {
    "name": "zomber-king-weapon",
    "mirror": false,
    "shootY": 10,
    "x": 16,
    "y": -4,
    "reload": 18,
    "shootSound": "sap",
    "bullet": {
      "type": "SapBulletType",
      "damage": 50,
      "length": 100,
      "sapStrength": "4",
      "shootEffect": "shootLiquid",
      "hitEffect": "hitLiquid",
      "color": "62AE7F",
      "lightColor": "84F491",
      "knockback": -5
    }
  }
]
}


    
